{
  "items": [
    {
      "type": "group",
      "ctime": 1746969063519,
      "items": [
        {
          "type": "group",
          "ctime": 1746970529189,
          "items": [
            {
              "type": "group",
              "ctime": 1746970536207,
              "items": [],
              "title": "HTML5"
            },
            {
              "type": "group",
              "ctime": 1746970533319,
              "items": [],
              "title": "CSS"
            },
            {
              "type": "group",
              "ctime": 1746970529189,
              "items": [],
              "title": "자바"
            },
            {
              "type": "group",
              "ctime": 1746970539631,
              "items": [],
              "title": "JavaScript"
            },
            {
              "type": "group",
              "ctime": 1746970539631,
              "items": [],
              "title": "LINUX"
            },
            {
              "type": "group",
              "ctime": 1746970539631,
              "items": [],
              "title": "Python"
            },
            {
              "type": "file",
              "ctime": 1746970539631,
              "path": "4. 프로그래밍 언어/sortspec.md.md",
              "subpath": "#^-"
            }
          ],
          "title": "4. 프로그래밍 언어"
        }
      ],
      "title": "sortspec"
    }
  ]
}